{
  "Duel": {
    "chapter": 11030072,
    "mat": [
      1090007,
      1090007
    ],
    "duel_object": [
      1100007,
      1100007
    ],
    "avatar_home": [
      1110007,
      1110007
    ],
    "name": [
      "Misty Tredwell",
      "Carly Carmine"
    ],
    "sleeve": [
      0,
      1070001
    ],
    "icon": [
      1010078,
      1010011
    ],
    "icon_frame": [
      0,
      1030004
    ],
    "avatar": [
      0,
      1002002
    ],
    "Deck": [
      {
        "Main": {
          "CardIds": [
            8629,
            8629,
            8456,
            8456,
            8457,
            8457,
            8627,
            8627,
            8627,
            8455,
            8455,
            14473,
            14473,
            14473,
            8628,
            8628,
            8628,
            6142,
            6142,
            6226,
            6226,
            8483,
            8484,
            8484,
            4844,
            4842,
            4343,
            7349,
            8485,
            8485,
            12175,
            8471,
            8471,
            8733,
            7522,
            7522,
            5818,
            7476,
            7476,
            8344,
            8344
          ],
          "Rare": [
            1,
            1,
            1,
            1,
            1,
            1,
            1,
            1,
            1,
            1,
            1,
            1,
            1,
            1,
            1,
            1,
            1,
            1,
            1,
            1,
            1,
            1,
            1,
            1,
            1,
            1,
            1,
            1,
            1,
            1,
            1,
            1,
            1,
            1,
            1,
            1,
            1,
            1,
            1,
            1,
            1
          ]
        },
        "Extra": {
          "CardIds": [
            8477,
            11667,
            8477,
            11667,
            8477,
            11667
          ],
          "Rare": [
            1,
            1,
            1,
            1,
            1,
            1
          ]
        },
        "Side": {
          "CardIds": [],
          "Rare": []
        }
      },
      {
        "Main": {
          "CardIds": [
            14554,
            14554,
            14554,
            14555,
            14555,
            14555,
            14551,
            14551,
            14551,
            14550,
            14550,
            14550,
            14552,
            14552,
            14552,
            14553,
            14553,
            14553,
            8446,
            8447,
            8302,
            8301,
            8301,
            14470,
            14470,
            14470,
            8444,
            8448,
            14509,
            14509,
            14558,
            14558,
            14556,
            14556,
            8344,
            8344,
            12963,
            12964,
            14557,
            14557,
            14557,
            14520,
            8341,
            8341
          ],
          "Rare": [
            1,
            1,
            1,
            1,
            1,
            1,
            1,
            1,
            1,
            1,
            1,
            1,
            1,
            1,
            1,
            1,
            1,
            1,
            1,
            1,
            1,
            1,
            1,
            1,
            1,
            1,
            1,
            1,
            1,
            1,
            1,
            1,
            1,
            1,
            1,
            1,
            1,
            1,
            1,
            1,
            1,
            1,
            1,
            1
          ]
        },
        "Extra": {
          "CardIds": [
            14486,
            14486,
            14486
          ],
          "Rare": [
            1,
            1,
            1
          ]
        },
        "Side": {
          "CardIds": [],
          "Rare": []
        }
      }
    ]
  }
}
