{
  "Duel": {
    "Deck": [
      {
        "Main": {
          "CardIds": [],
          "Rare": []
        },
        "Extra": {
          "CardIds": [],
          "Rare": []
        },
        "Side": {
          "CardIds": [],
          "Rare": []
        }
      },
      {
        "Main": {
          "CardIds": [
            5561,
            5561,
            5561,
            7359,
            7359,
            10763,
            10763,
            10763,
            5423,
            5423,
            5423,
            7215,
            7215,
            7215,
            4930,
            4930,
            4930,
            6564,
            6564,
            6564,
            7399,
            7399,
            7399,
            4938,
            4938,
            4938,
            8826,
            8826,
            8826,
            9775,
            9775,
            9775,
            8344,
            8344,
            8344,
            5614,
            5614,
            7636,
            7636,
            7636
          ],
          "Rare": [
            1,
            1,
            1,
            1,
            1,
            1,
            1,
            1,
            1,
            1,
            1,
            1,
            1,
            1,
            1,
            1,
            1,
            1,
            1,
            1,
            1,
            1,
            1,
            1,
            1,
            1,
            1,
            1,
            1,
            1,
            1,
            1,
            1,
            1,
            1,
            1,
            1,
            1,
            1,
            1
          ]
        },
        "Extra": {
          "CardIds": [
            9963,
            9963,
            9963,
            10933,
            10933,
            10933,
            11071,
            11071,
            11071
          ],
          "Rare": [
            1,
            1,
            1,
            1,
            1,
            1,
            1,
            1,
            1
          ]
        },
        "Side": {
          "CardIds": [],
          "Rare": []
        }
      }
    ],
    "chapter": 11110010,
    "mat": [
      1090001,
      1090001
    ],
    "duel_object": [
      1100001,
      1100001
    ],
    "avatar_home": [
      1110001,
      1110001
    ],
    "name": [
      "",
      "Panik"
    ],
    "sleeve": [
      0,
      1070014
    ],
    "icon": [
      0,
      1010028
    ],
    "icon_frame": [
      0,
      1030013
    ],
    "avatar": [
      0,
      1002010
    ]
  }
}