{
  "Duel": {
    "Deck": [
      {
        "Main": {
          "CardIds": [],
          "Rare": []
        },
        "Extra": {
          "CardIds": [],
          "Rare": []
        },
        "Side": {
          "CardIds": [],
          "Rare": []
        }
      },
      {
        "Main": {
          "CardIds": [
            5927,
            5927,
            5927,
            10166,
            10166,
            10166,
            10219,
            10221,
            10221,
            10221,
            10220,
            10220,
            10220,
            6928,
            6928,
            8187,
            8187,
            8187,
            10514,
            10514,
            10514,
            10218,
            10218,
            10222,
            10222,
            8493,
            8493,
            4909,
            4343,
            5908,
            5908,
            5908,
            11159,
            8366,
            8366,
            4989,
            8687,
            8687,
            8687,
            5114
          ],
          "Rare": [
            1,
            1,
            1,
            1,
            1,
            1,
            1,
            1,
            1,
            1,
            1,
            1,
            1,
            1,
            1,
            1,
            1,
            1,
            1,
            1,
            1,
            1,
            1,
            1,
            1,
            1,
            1,
            1,
            1,
            1,
            1,
            1,
            1,
            1,
            1,
            1,
            1,
            1,
            1,
            1
          ]
        },
        "Extra": {
          "CardIds": [
            7552,
            10648,
            10648,
            7987,
            9801,
            7970,
            7736,
            8262,
            8262,
            7549,
            8196,
            10647,
            9656,
            9656,
            9656
          ],
          "Rare": [
            1,
            1,
            1,
            1,
            1,
            1,
            1,
            1,
            1,
            1,
            1,
            1,
            1,
            1,
            1
          ]
        },
        "Side": {
          "CardIds": [],
          "Rare": []
        }
      }
    ],
    "chapter": 11140015,
    "mat": [
      1090001,
      1090001
    ],
    "duel_object": [
      1100001,
      1100001
    ],
    "avatar_home": [
      1110001,
      1110001
    ],
    "name": [
      "",
      "Nash"
    ],
    "sleeve": [
      0,
      1070014
    ],
    "icon": [
      0,
      1010028
    ],
    "icon_frame": [
      0,
      1030013
    ],
    "avatar": [
      0,
      1002010
    ]
  }
}