{
  "Duel": {
    "Deck": [
      {
        "Main": {
          "CardIds": [],
          "Rare": []
        },
        "Extra": {
          "CardIds": [],
          "Rare": []
        },
        "Side": {
          "CardIds": [],
          "Rare": []
        }
      },
      {
        "Main": {
          "CardIds": [
            12606,
            12606,
            12606,
            12607,
            12607,
            12605,
            12605,
            12605,
            12755,
            12755,
            12755,
            12610,
            12610,
            12610,
            12608,
            12608,
            12608,
            12756,
            12756,
            12609,
            12609,
            12609,
            11708,
            11708,
            11708,
            12647,
            12647,
            10274,
            10274,
            10274,
            10008,
            10008,
            10008,
            5389,
            5389,
            12175,
            12661,
            12662,
            12662,
            12662
          ],
          "Rare": [
            1,
            1,
            1,
            1,
            1,
            1,
            1,
            1,
            1,
            1,
            1,
            1,
            1,
            1,
            1,
            1,
            1,
            1,
            1,
            1,
            1,
            1,
            1,
            1,
            1,
            1,
            1,
            1,
            1,
            1,
            1,
            1,
            1,
            1,
            1,
            1,
            1,
            1,
            1,
            1
          ]
        },
        "Extra": {
          "CardIds": [
            12450,
            12450,
            7836,
            12635,
            12635,
            12636,
            12636,
            12634,
            12634,
            12781,
            12781,
            8035,
            12779,
            11660,
            11660
          ],
          "Rare": [
            1,
            1,
            1,
            1,
            1,
            1,
            1,
            1,
            1,
            1,
            1,
            1,
            1,
            1,
            1
          ]
        },
        "Side": {
          "CardIds": [],
          "Rare": []
        }
      }
    ],
    "chapter": 11150006,
    "mat": [
      1090001,
      1090001
    ],
    "duel_object": [
      1100001,
      1100001
    ],
    "avatar_home": [
      1110001,
      1110001
    ],
    "name": [
      "",
      "Crow Hogan"
    ],
    "sleeve": [
      0,
      1070014
    ],
    "icon": [
      0,
      1010028
    ],
    "icon_frame": [
      0,
      1030013
    ],
    "avatar": [
      0,
      1002010
    ]
  }
}